sahl_nutun_common/api.py
sahl_nutun_common/constants.py
sahl_nutun_common/download.zip
sahl_nutun_common/project_details.py
sahl_nutun_common/sqs.py
sahl_nutun_common/test1.zip
sahl_nutun_common/z/account_details_xxxxx13928.json
sahl_nutun_common/z/address.json
sahl_nutun_common/z/affordability.json
sahl_nutun_common/z/affordability_xxxxx13928.json
sahl_nutun_common/z/beneficiaries.json
sahl_nutun_common/z/contact_details.json
sahl_nutun_common/z/download.zip
sahl_nutun_common/z/income_transactions.json
sahl_nutun_common/z/income_transactions_xxxxx13928.json
sahl_nutun_common/z/pay_date_indicators.json
sahl_nutun_common/z/pay_date_indicators_xxxxx13928.json
sahl_nutun_common/z/personal_info.json
sahl_nutun_common/z/transaction_history_debit_order.json
sahl_nutun_common/z/transaction_history_debit_order_xxxxx13928.json
sahl_nutun_common/z/transaction_history_xxxxx13928.json
sahl_nutun_common-0.2.0.dist-info/WHEEL
sahl_nutun_common-0.2.0.dist-info/METADATA
sahl_nutun_common-0.2.0.dist-info/RECORD
