Metadata-Version: 2.1
Name: sahl-nutun-common
Version: 0.2.0
Summary: Common modules for Nutun Authentifi interaction, including authenticated API calling
Author: kimv
Author-email: kimv@sahomeloans.com
Requires-Python: >=3.9,<4.0
Classifier: Programming Language :: Python :: 3
Classifier: Programming Language :: Python :: 3.9
Classifier: Programming Language :: Python :: 3.10
Classifier: Programming Language :: Python :: 3.11
Requires-Dist: attrs (>=22.2.0,<23.0.0)
Requires-Dist: boto3 (>=1.26.89,<2.0.0)
Requires-Dist: httpx (>=0.23.3,<0.24.0)
Requires-Dist: ptpython (>=3.0.23,<4.0.0)
Requires-Dist: pyjwt (>=2.6.0,<3.0.0)
Requires-Dist: python-dotenv (>=1.0.0,<2.0.0)
Requires-Dist: rich (>=13.3.2,<14.0.0)
